[
    {
        "name": "Aridia",
        "chest_unopened_img": "/images/items/close.png",
        "chest_opened_img": "/images/items/open.png",
        "access_rules": [ "Aridia" ],
        "children": [
            {
                "name": "Construction Zone",
                "chest_unopened_img": "/images/items/Mission.png",
                "access_rules": [ "Swingshot" ],
                "sections": [
                    {
                        "name": "Reward",
                        "item_count": 1
                    },
                    {
                        "name": "Gold Bolt",
                        "chest_unopened_img": "/images/items/GoldBolt.png",
                        "visibility_rules": [ "Bolt" ],
                        "item_count": 1
                    }
                ],
                "map_locations": [
                    {
                        "map": "Aridia",
                        "x": "107",
                        "y": "113",
                        "size": 14
                    }
                ]
            },
            {
                "name": "Laser",
                "visibility_rules": [ "Bolt" ],
                "chest_unopened_img": "/images/items/GoldBolt.png",
                "access_rules": [ "Magneboots" ],
                "sections": [
                    {
                        "name": "Gold Bolt",
                        "item_count": 1
                    }
                ],
                "map_locations": [
                    {
                        "map": "Aridia",
                        "x": "367",
                        "y": "57",
                        "size": 14
                    }
                ]
            },
            {
                "name": "Island",
                "visibility_rules": [ "Bolt" ],
                "chest_unopened_img": "/images/items/GoldBolt.png",
                "sections": [
                    {
                        "name": "Gold Bolt",
                        "item_count": 1
                    }
                ],
                "map_locations": [
                    {
                        "map": "Aridia",
                        "x": "385",
                        "y": "248",
                        "size": 14
                    }
                ]
            },
            {
                "name": "Sandshark Cave",
                "access_rules": [ "BombGlove", "MineGlove", "Devastator", "Visibomb", "RYNO" ],
                "chest_unopened_img": "/images/items/GoldBolt.png",
                "visibility_rules": [ "Bolt" ],
                "sections": [
                    {
                        "name": "Gold Bolt",
                        "item_count": 1
                    }
                ],
                "map_locations": [
                    {
                        "map": "Aridia",
                        "x": "253",
                        "y": "431",
                        "size": 14
                    }
                ]
            },
            {
                "name": "Transported",
                "visibility_rules": [ "AmondoTrap" ],
                "access_rules": [ "SuckCannon", "Blaster", "Pyrocitor", "TeslaClaw", "Devastator", "Visibomb", "RYNO" ],
                "chest_unopened_img": "/images/items/Skill.png",
                "sections": [
                    {
                        "name": "Destroy three flying transports ",
                        "item_count": 1
                    }
                ],
                "map_locations": [
                    {
                        "map": "Aridia",
                        "x": "302",
                        "y": "292",
                        "size": 14
                    }
                ]
            },
            {
                "name": "Swing It!",
                "visibility_rules": [ "AmondoTrap" ],
                "chest_unopened_img": "/images/items/Skill.png",
                "access_rules": [ "Swingshot" ],
                "sections": [
                    {
                        "name": "Traverse final six swingshot targets in factory without touching the ground ",
                        "item_count": 1
                    }
                ],
                "map_locations": [
                    {
                        "map": "Aridia",
                        "x": "76",
                        "y": "134",
                        "size": 14
                    }
                ]
            },
            {
                "name": "Kill the Sand Sharks",
                "chest_unopened_img": "/images/items/Mission.png",
                "sections": [
                    {
                        "item_count": 1
                    }
                ],
                "map_locations": [
                    {
                        "map": "Aridia",
                        "x": "252",
                        "y": "352",
                        "size": 14
                    }
                ]
            },
            {
                "name": "Bring Zoomerator to Agent",
                "chest_unopened_img": "/images/items/Mission.png",
                "access_rules": ["Zoomerator"],
                "sections": [
                    {
                        "item_count": 1
                    }
                ],
                "map_locations": [
                    {
                        "map": "Aridia",
                        "x": "391",
                        "y": "131",
                        "size": 14
                    }
                ]
            }
        ]
    }
]